Metadata-Version: 1.0
Name: distributions-meysam
Version: 0.1
Summary: Gaussian and Binomial distributions
Home-page: UNKNOWN
Author: meysam hadigheh
Author-email: hadigheh.meysam@gmail.com
License: UNKNOWN
Platform: UNKNOWN
